superduper_vllm/__init__.py
superduper_vllm/model.py
superduper_vllm-0.10.0.dist-info/licenses/LICENSE
superduper_vllm-0.10.0.dist-info/METADATA
superduper_vllm-0.10.0.dist-info/WHEEL
superduper_vllm-0.10.0.dist-info/top_level.txt
superduper_vllm-0.10.0.dist-info/RECORD
