Metadata-Version: 2.4
Name: superduper_vllm
Version: 0.10.0
Summary: Superduper allows users to work with self-hosted LLM models via [vLLM](https://github.com/vllm-project/vllm).
Maintainer-email: "superduper.io, Inc." <opensource@superduper.io>
License: 
Project-URL: homepage, https://superduper.io
Project-URL: documentation, https://docs.superduper.io/docs/intro
Project-URL: source, https://github.com/superduper-io/superduper
Keywords: databases,mongodb,data-science,machine-learning,mlops,vector-database,ai
Requires-Python: >=3.10
License-File: LICENSE
Requires-Dist: vllm
Provides-Extra: test
Requires-Dist: pytest-asyncio; extra == "test"
Dynamic: license-file
